HiLinkAPI.py
hilinkapi-2.0.0.dist-info/licenses/LICENSE
hilinkapi-2.0.0.dist-info/METADATA
hilinkapi-2.0.0.dist-info/WHEEL
hilinkapi-2.0.0.dist-info/top_level.txt
hilinkapi-2.0.0.dist-info/RECORD
